transmog/__init__.py
transmog/api.py
transmog/config.py
transmog/exceptions.py
transmog/flattening.py
transmog/iterators.py
transmog/streaming.py
transmog/types.py
transmog/writers/__init__.py
transmog/writers/arrow_base.py
transmog/writers/base.py
transmog/writers/csv.py
transmog/writers/orc.py
transmog/writers/parquet.py
transmog-2.0.1.dist-info/METADATA
transmog-2.0.1.dist-info/WHEEL
transmog-2.0.1.dist-info/licenses/LICENSE
transmog-2.0.1.dist-info/RECORD
