Metadata-Version: 2.4
Name: transmog
Version: 2.0.1
Summary: A data transformation library for flattening complex nested structures into tabular formats while preserving hierarchical relationships
License-Expression: MIT
License-File: LICENSE
Keywords: csv,data-pipeline,data-processing,data-transformation,elt,etl,flattening,json,normalization,parquet,pyarrow
Author: Scott Draper
Author-email: admin@scottdraper.io
Requires-Python: >=3.10
Classifier: Development Status :: 3 - Alpha
Classifier: Intended Audience :: Developers
Classifier: Intended Audience :: Information Technology
Classifier: Programming Language :: Python :: 3 :: Only
Classifier: Programming Language :: Python :: 3.10
Classifier: Programming Language :: Python :: 3.11
Classifier: Programming Language :: Python :: 3.12
Classifier: Programming Language :: Python :: 3.13
Classifier: Programming Language :: Python :: 3.14
Classifier: Topic :: Database :: Database Engines/Servers
Classifier: Topic :: Software Development :: Libraries :: Python Modules
Provides-Extra: dev
Provides-Extra: minimal
Requires-Dist: bandit (>=1.7.5) ; extra == "dev"
Requires-Dist: furo (>=2024.1.29) ; extra == "dev"
Requires-Dist: hjson (>=3.1)
Requires-Dist: hjson (>=3.1) ; extra == "minimal"
Requires-Dist: interrogate (>=1.5) ; extra == "dev"
Requires-Dist: json5 (>=0.9)
Requires-Dist: json5 (>=0.9) ; extra == "minimal"
Requires-Dist: linkify-it-py (>=2) ; extra == "dev"
Requires-Dist: memory-profiler (>=0.60) ; extra == "dev"
Requires-Dist: mypy (>=0.9) ; extra == "dev"
Requires-Dist: myst-parser (>=2) ; extra == "dev"
Requires-Dist: orjson (>=3.8)
Requires-Dist: orjson (>=3.8) ; extra == "minimal"
Requires-Dist: pre-commit (>=3.5) ; extra == "dev"
Requires-Dist: psutil (>=5.8) ; extra == "dev"
Requires-Dist: pyarrow (>=7)
Requires-Dist: pyproject-fmt (>=1.5.1) ; extra == "dev"
Requires-Dist: pyproject-parser (>=0.7) ; extra == "dev"
Requires-Dist: pytest (>=7) ; extra == "dev"
Requires-Dist: pytest-benchmark (>=4) ; extra == "dev"
Requires-Dist: pytest-cov (>=3) ; extra == "dev"
Requires-Dist: ruff (>=0.3) ; extra == "dev"
Requires-Dist: safety (>=2.3.5) ; extra == "dev"
Requires-Dist: sphinx (>=7.2) ; extra == "dev"
Requires-Dist: sphinx-autobuild (>=2021.3.14) ; extra == "dev"
Requires-Dist: sphinx-autodoc-typehints (>=1.24) ; extra == "dev"
Requires-Dist: sphinx-copybutton (>=0.5) ; extra == "dev"
Requires-Dist: sphinx-design (>=0.5) ; extra == "dev"
Requires-Dist: sphinx-rtd-theme (>=2) ; extra == "dev"
Requires-Dist: sphinxcontrib-applehelp (>=1) ; extra == "dev"
Requires-Dist: sphinxcontrib-htmlhelp (>=2) ; extra == "dev"
Requires-Dist: sphinxcontrib-jsmath (>=1) ; extra == "dev"
Requires-Dist: sphinxcontrib-mermaid (>=0.8.1) ; extra == "dev"
Requires-Dist: sphinxcontrib-napoleon (>=0.7) ; extra == "dev"
Requires-Dist: sphinxcontrib-qthelp (>=1) ; extra == "dev"
Requires-Dist: sphinxcontrib-serializinghtml (>=1) ; extra == "dev"
Requires-Dist: types-pyyaml ; extra == "dev"
Requires-Dist: types-toml ; extra == "dev"
Requires-Dist: typing-extensions (>=4)
Requires-Dist: typing-extensions (>=4) ; extra == "minimal"
Project-URL: Bug Tracker, https://github.com/scottdraper8/transmog/issues
Project-URL: Documentation, https://scottdraper8.github.io/transmog/
Project-URL: Homepage, https://github.com/scottdraper8/transmog
